{"cameraMode":{"drawMode":0,"name":"Shaded","section":"Shading Mode"},"sceneLighting":false,"audioPlay":false,"sceneViewState":{"m_AlwaysRefresh":false,"showFog":true,"showSkybox":false,"showFlares":true,"showImageEffects":true,"showParticleSystems":true,"showVisualEffectGraphs":true,"m_FxEnabled":true},"in2DMode":false,"pivot":{"x":-0.5788580179214478,"y":-0.48580968379974368,"z":0.9895145893096924},"rotation":{"x":-0.245177760720253,"y":0.7125259041786194,"z":-0.2981567084789276,"w":-0.5859196186065674},"size":1.0792253017425538,"orthographic":false}